navigation_2d/__init__.py
navigation_2d/config.py
navigation_2d/navigation_env.py
navigation_2d/objects.py
navigation_2d/util.py
navigation_2d-1.5.0.dist-info/METADATA
navigation_2d-1.5.0.dist-info/WHEEL
navigation_2d-1.5.0.dist-info/top_level.txt
navigation_2d-1.5.0.dist-info/RECORD
